[
  {
    "id": "4YhDAuRzHyU",
    "title": "Que hacemos en Home Auto Restorer ",
    "description": "",
    "publishedAt": "2026-01-30T15:13:17Z",
    "thumbnail": "https://i.ytimg.com/vi/4YhDAuRzHyU/hqdefault.jpg"
  },
  {
    "id": "KN7b9fJTJtQ",
    "title": "Parte 14 - restaurando bultaco mercurio de 1962",
    "description": "Restaurando asiento de la bultaco mercurio 125 usando método low cost. Por 8€ y tiempo puedes hacer una funda bien ajustada ...",
    "publishedAt": "2026-01-01T19:49:15Z",
    "thumbnail": "https://i.ytimg.com/vi/KN7b9fJTJtQ/hqdefault.jpg"
  },
  {
    "id": "HTFb8lFPCAc",
    "title": "Bultaco Mercurio - Cerrar carter motor",
    "description": "Como cerrar el carte de motor sin problemas de la Bultaco Mercurio.",
    "publishedAt": "2025-11-09T10:40:04Z",
    "thumbnail": "https://i.ytimg.com/vi/HTFb8lFPCAc/hqdefault.jpg"
  },
  {
    "id": "nlLiK15YTrE",
    "title": "Parte 11 - Desmontando lo que queda de la bultaco mercurio de 1962 ",
    "description": "Estado lamentable pero poco a poco irá recibiendo mimos.",
    "publishedAt": "2025-11-08T09:14:25Z",
    "thumbnail": "https://i.ytimg.com/vi/nlLiK15YTrE/hqdefault.jpg"
  },
  {
    "id": "3VksCVEwzEo",
    "title": "Parte 10 - Proceso completo motor bultaco mercurio 1962",
    "description": "Proceso completo de restauración del motor.",
    "publishedAt": "2025-11-07T17:58:36Z",
    "thumbnail": "https://i.ytimg.com/vi/3VksCVEwzEo/hqdefault.jpg"
  }
]